README.md
setup.py
opplast/__init__.py
opplast/constants.py
opplast/exceptions.py
opplast/logging.py
opplast/upload.py
opplast.egg-info/PKG-INFO
opplast.egg-info/SOURCES.txt
opplast.egg-info/dependency_links.txt
opplast.egg-info/requires.txt
opplast.egg-info/top_level.txt