Metadata-Version: 2.1
Name: opplast
Version: 1.0.14
Summary: Upload videos to YouTube using geckodriver, Firefox profiles and Selenium.
Home-page: https://github.com/offish/opplast
Author: offish
Author-email: overutilization@gmail.com
License: MIT
Download-URL: https://github.com/offish/opplast/tarball/v1.0.14
Platform: UNKNOWN
Classifier: Programming Language :: Python :: 3
Classifier: License :: OSI Approved :: MIT License
Classifier: Operating System :: OS Independent
Requires-Python: >=3.6
